FuzzysecurityWindowsExploitKaifaXilieJiaocheng18/README.md
FuzzysecurityWindowsExploitKaifaXilieJiaocheng18/__init__.py
FuzzysecurityWindowsExploitKaifaXilieJiaocheng18/__main__.py
FuzzysecurityWindowsExploitKaifaXilieJiaocheng18/file.epub
FuzzysecurityWindowsExploitKaifaXilieJiaocheng18/index.html
FuzzysecurityWindowsExploitKaifaXilieJiaocheng18/css/__init__.py
FuzzysecurityWindowsExploitKaifaXilieJiaocheng18/css/annotations.css
FuzzysecurityWindowsExploitKaifaXilieJiaocheng18/css/main.css
FuzzysecurityWindowsExploitKaifaXilieJiaocheng18/css/normalize.css
FuzzysecurityWindowsExploitKaifaXilieJiaocheng18/css/popup.css
FuzzysecurityWindowsExploitKaifaXilieJiaocheng18/font/__init__.py
FuzzysecurityWindowsExploitKaifaXilieJiaocheng18/font/fontello.eot
FuzzysecurityWindowsExploitKaifaXilieJiaocheng18/font/fontello.svg
FuzzysecurityWindowsExploitKaifaXilieJiaocheng18/font/fontello.ttf
FuzzysecurityWindowsExploitKaifaXilieJiaocheng18/font/fontello.woff
FuzzysecurityWindowsExploitKaifaXilieJiaocheng18/img/__init__.py
FuzzysecurityWindowsExploitKaifaXilieJiaocheng18/img/annotator-glyph-sprite.png
FuzzysecurityWindowsExploitKaifaXilieJiaocheng18/img/annotator-icon-sprite.png
FuzzysecurityWindowsExploitKaifaXilieJiaocheng18/img/apple-touch-icon.png
FuzzysecurityWindowsExploitKaifaXilieJiaocheng18/img/cancelfullscreen.png
FuzzysecurityWindowsExploitKaifaXilieJiaocheng18/img/close.png
FuzzysecurityWindowsExploitKaifaXilieJiaocheng18/img/fullscreen.png
FuzzysecurityWindowsExploitKaifaXilieJiaocheng18/img/loader.gif
FuzzysecurityWindowsExploitKaifaXilieJiaocheng18/img/menu-icon.png
FuzzysecurityWindowsExploitKaifaXilieJiaocheng18/img/save.png
FuzzysecurityWindowsExploitKaifaXilieJiaocheng18/img/saved.png
FuzzysecurityWindowsExploitKaifaXilieJiaocheng18/img/settings-s.png
FuzzysecurityWindowsExploitKaifaXilieJiaocheng18/img/settings.png
FuzzysecurityWindowsExploitKaifaXilieJiaocheng18/img/star.png
FuzzysecurityWindowsExploitKaifaXilieJiaocheng18/js/__init__.py
fuzzysecurity_windows_exploit_kaifa_xilie_jiaocheng_1_8-2024.3.2.0.dist-info/METADATA
fuzzysecurity_windows_exploit_kaifa_xilie_jiaocheng_1_8-2024.3.2.0.dist-info/WHEEL
fuzzysecurity_windows_exploit_kaifa_xilie_jiaocheng_1_8-2024.3.2.0.dist-info/entry_points.txt
fuzzysecurity_windows_exploit_kaifa_xilie_jiaocheng_1_8-2024.3.2.0.dist-info/top_level.txt
fuzzysecurity_windows_exploit_kaifa_xilie_jiaocheng_1_8-2024.3.2.0.dist-info/RECORD
